{
  "data" : [ {
    "id" : "688128",
    "type" : "users",
    "attributes" : {
      "updatePassword" : false,
      "gender" : "FEMALE",
      "displayName" : null,
      "credentialsNonExpired" : true,
      "roles" : [ {
        "id" : 1,
        "createdAt" : 1493972521017,
        "name" : "ROLE_ADMINISTRATOR"
      }, {
        "id" : 2,
        "createdAt" : 1493972521093,
        "name" : "ROLE_USER"
      } ],
      "mobile" : null,
      "mobileVerified" : false,
      "avatar" : null,
      "enabled" : true,
      "emailVerified" : true,
      "createdAt" : null,
      "password" : null,
      "name" : "admin",
      "accountNonExpired" : true,
      "email" : "admin@m3958.com",
      "accountNonLocked" : true
    },
    "relationships" : {
      "mysites" : {
        "links" : {
          "self" : "http://localhost:8080/jsonapi/users/688128/relationships/mysites",
          "related" : "http://localhost:8080/jsonapi/users/688128/mysites"
        }
      }
    },
    "links" : {
      "self" : "http://localhost:8080/jsonapi/users/688128"
    }
  } ],
  "links" : {
    "first" : "http://localhost:8080/jsonapi/users/?page[limit]=20",
    "last" : "http://localhost:8080/jsonapi/users/?page[limit]=20",
    "next" : null,
    "prev" : null
  },
  "meta" : {
    "totalResourceCount" : 1
  }
}